[
  {
    "id": "kr2-01",
    "country": "kr",
    "name_zh": "朝鮮美人 米萃益生菌防曬",
    "name_local": "조선미녀 릴리프 선",
    "category": "beauty",
    "emoji": "🧴",
    "price_local": "₩10,000-16,000",
    "price_twd": "約 NT$230-370",
    "save_stars": 5,
    "reason": "韓妝部落客零負評防曬，清爽不泛白，台灣貴一倍",
    "where": ["Olive Young", "藥妝店"],
    "maps_query": "올리브영",
    "region_note": null,
    "editor_rank": 21
  },
  {
    "id": "kr2-02",
    "country": "kr",
    "name_zh": "COSRX 96% 蝸牛黏液精華",
    "name_local": "코스알엑스 스네일 96 뮤신 에센스",
    "category": "beauty",
    "emoji": "🐌",
    "price_local": "₩16,000-22,000",
    "price_twd": "約 NT$370-510",
    "save_stars": 4,
    "reason": "修復爛臉神器，96%蝸牛黏液，保養新手也不踩雷",
    "where": ["Olive Young", "藥妝店"],
    "maps_query": "올리브영",
    "region_note": null,
    "editor_rank": 22
  },
  {
    "id": "kr2-03",
    "country": "kr",
    "name_zh": "Anua 魚腥草 77% 舒緩化妝水",
    "name_local": "아누아 어성초 77 토너",
    "category": "beauty",
    "emoji": "💧",
    "price_local": "₩18,000-24,000",
    "price_twd": "約 NT$410-550",
    "save_stars": 4,
    "reason": "TikTok爆紅油痘肌救星，鎮定又控油超好用",
    "where": ["Olive Young", "藥妝店"],
    "maps_query": "올리브영",
    "region_note": null,
    "editor_rank": 23
  },
  {
    "id": "kr2-04",
    "country": "kr",
    "name_zh": "Numbuzin 3號 嫩肌提亮精華",
    "name_local": "넘버즈인 3번 세럼",
    "category": "beauty",
    "emoji": "✨",
    "price_local": "₩22,000-28,000",
    "price_twd": "約 NT$500-640",
    "save_stars": 4,
    "reason": "編號系列提亮明星，上臉透亮像開燈",
    "where": ["Olive Young", "藥妝店"],
    "maps_query": "올리브영",
    "region_note": null,
    "editor_rank": 24
  },
  {
    "id": "kr2-05",
    "country": "kr",
    "name_zh": "朝鮮美人 光曜緊緻精華",
    "name_local": "조선미녀 글로우 딥 세럼",
    "category": "beauty",
    "emoji": "🌟",
    "price_local": "₩12,000-17,000",
    "price_twd": "約 NT$280-390",
    "save_stars": 5,
    "reason": "米萃提亮精華，暗沉肌用了會發光，CP值高",
    "where": ["Olive Young", "藥妝店"],
    "maps_query": "올리브영",
    "region_note": null,
    "editor_rank": 25
  },
  {
    "id": "kr2-06",
    "country": "kr",
    "name_zh": "Dasique 九宮格眼影盤",
    "name_local": "데이지크 섀도우 팔레트",
    "category": "beauty",
    "emoji": "🎨",
    "price_local": "₩18,000-24,000",
    "price_twd": "約 NT$410-550",
    "save_stars": 4,
    "reason": "平價版3CE，粉質細膩顯色，色調柔和百搭",
    "where": ["Olive Young", "美妝店"],
    "maps_query": "올리브영",
    "region_note": null,
    "editor_rank": 26
  },
  {
    "id": "kr2-07",
    "country": "kr",
    "name_zh": "SKIN1004 積雪草鎮定安瓶",
    "name_local": "스킨천사 마다가스카르 센텔라 앰플",
    "category": "beauty",
    "emoji": "🌿",
    "price_local": "₩18,000-25,000",
    "price_twd": "約 NT$410-580",
    "save_stars": 4,
    "reason": "積雪草鎮定泛紅，敏感肌一整年回購款",
    "where": ["Olive Young", "藥妝店"],
    "maps_query": "올리브영",
    "region_note": null,
    "editor_rank": 27
  },
  {
    "id": "kr2-08",
    "country": "kr",
    "name_zh": "hince 自然裸感腮紅",
    "name_local": "힌스 트루 디멘션 블러셔",
    "category": "beauty",
    "emoji": "💗",
    "price_local": "₩18,000-23,000",
    "price_twd": "約 NT$410-530",
    "save_stars": 3,
    "reason": "自然好氣色腮紅，色號多又不顯色塊",
    "where": ["Olive Young", "美妝店"],
    "maps_query": "올리브영",
    "region_note": null,
    "editor_rank": 28
  },
  {
    "id": "kr2-09",
    "country": "kr",
    "name_zh": "Unove 深層修護髮膜",
    "name_local": "우노브 딥 데미지 트리트먼트",
    "category": "daily",
    "emoji": "💆",
    "price_local": "₩13,000-18,000",
    "price_twd": "約 NT$300-410",
    "save_stars": 4,
    "reason": "毛躁髮救星，敷一次髮尾立刻滑順",
    "where": ["Olive Young", "藥妝店"],
    "maps_query": "올리브영",
    "region_note": null,
    "editor_rank": 29
  },
  {
    "id": "kr2-10",
    "country": "kr",
    "name_zh": "呂 Ryo 人參防脫洗髮精",
    "name_local": "려 탈모 케어 샴푸",
    "category": "daily",
    "emoji": "🚿",
    "price_local": "₩12,000-18,000",
    "price_twd": "約 NT$280-410",
    "save_stars": 3,
    "reason": "漢方養髮控油，掉髮困擾必試的國民洗髮精",
    "where": ["Olive Young", "樂天超市", "藥妝店"],
    "maps_query": "올리브영",
    "region_note": null,
    "editor_rank": 30
  },
  {
    "id": "kr2-11",
    "country": "kr",
    "name_zh": "LABO-H 頭皮養髮精華",
    "name_local": "라보에이치 두피 강화 토닉",
    "category": "daily",
    "emoji": "🌱",
    "price_local": "₩25,000-33,000",
    "price_twd": "約 NT$580-760",
    "save_stars": 3,
    "reason": "頭皮養髮精華，掉髮族群狂推，台灣少見",
    "where": ["Olive Young", "藥妝店"],
    "maps_query": "올리브영",
    "region_note": null,
    "editor_rank": 31
  },
  {
    "id": "kr2-12",
    "country": "kr",
    "name_zh": "大創 Daiso 生活小物",
    "name_local": "다이소 생활용품",
    "category": "daily",
    "emoji": "🛒",
    "price_local": "₩1,000-5,000",
    "price_twd": "約 NT$25-115",
    "save_stars": 5,
    "reason": "生活雜貨挖寶天堂，銅板價買到手軟",
    "where": ["大創 Daiso"],
    "maps_query": "다이소",
    "region_note": null,
    "editor_rank": 32
  },
  {
    "id": "kr2-13",
    "country": "kr",
    "name_zh": "韓式萬用廚房剪刀",
    "name_local": "주방 가위",
    "category": "daily",
    "emoji": "✂️",
    "price_local": "₩5,000-12,000",
    "price_twd": "約 NT$115-280",
    "save_stars": 3,
    "reason": "韓式萬用廚房剪，剪肉剪菜超好用又耐用",
    "where": ["大創 Daiso", "樂天超市"],
    "maps_query": "다이소",
    "region_note": null,
    "editor_rank": 33
  },
  {
    "id": "kr2-14",
    "country": "kr",
    "name_zh": "爽快丸 醒酒丸",
    "name_local": "상쾌환",
    "category": "health",
    "emoji": "🍶",
    "price_local": "₩8,000-15,000",
    "price_twd": "約 NT$180-350",
    "save_stars": 5,
    "reason": "喝酒前後一條，隔天不頭痛，台灣很難買",
    "where": ["便利商店", "藥局", "Olive Young"],
    "maps_query": "편의점",
    "region_note": null,
    "editor_rank": 34
  },
  {
    "id": "kr2-15",
    "country": "kr",
    "name_zh": "熊膽 Ursa 護肝錠",
    "name_local": "우루사",
    "category": "health",
    "emoji": "🫀",
    "price_local": "₩10,000-20,000",
    "price_twd": "約 NT$230-460",
    "save_stars": 4,
    "reason": "應酬族護肝人氣藥品，藥局就買得到",
    "where": ["藥局"],
    "maps_query": "약국",
    "region_note": null,
    "editor_rank": 35
  },
  {
    "id": "kr2-16",
    "country": "kr",
    "name_zh": "活命水 消化液",
    "name_local": "까스활명수",
    "category": "health",
    "emoji": "🥤",
    "price_local": "₩5,000-9,000",
    "price_twd": "約 NT$115-210",
    "save_stars": 4,
    "reason": "國民消化液，吃太飽脹氣喝一瓶超有感",
    "where": ["藥局", "便利商店"],
    "maps_query": "약국",
    "region_note": null,
    "editor_rank": 36
  },
  {
    "id": "kr2-17",
    "country": "kr",
    "name_zh": "馬德卡索 積雪草修護藥膏",
    "name_local": "마데카솔",
    "category": "health",
    "emoji": "🩹",
    "price_local": "₩5,000-9,000",
    "price_twd": "約 NT$115-210",
    "save_stars": 4,
    "reason": "積雪草修護傷口藥膏，韓國家庭常備藥",
    "where": ["藥局"],
    "maps_query": "약국",
    "region_note": null,
    "editor_rank": 37
  },
  {
    "id": "kr2-18",
    "country": "kr",
    "name_zh": "판피린Q 感冒糖漿",
    "name_local": "판피린큐",
    "category": "health",
    "emoji": "💊",
    "price_local": "₩6,000-10,000",
    "price_twd": "約 NT$140-230",
    "save_stars": 3,
    "reason": "韓國國民感冒糖漿，喉嚨不舒服來一瓶",
    "where": ["藥局"],
    "maps_query": "약국",
    "region_note": null,
    "editor_rank": 38
  },
  {
    "id": "kr2-19",
    "country": "kr",
    "name_zh": "蜂蜜柚子茶",
    "name_local": "꿀 유자차",
    "category": "souvenir",
    "emoji": "🍵",
    "price_local": "₩8,000-15,000",
    "price_twd": "約 NT$180-350",
    "save_stars": 3,
    "reason": "沖泡蜂蜜柚子茶，暖身又潤喉，送禮自用皆宜",
    "where": ["樂天超市", "便利商店"],
    "maps_query": "롯데마트",
    "region_note": null,
    "editor_rank": 39
  },
  {
    "id": "kr2-20",
    "country": "kr",
    "name_zh": "星巴克韓國限定城市杯",
    "name_local": "스타벅스 코리아 시티 텀블러",
    "category": "souvenir",
    "emoji": "🏙️",
    "price_local": "₩25,000-35,000",
    "price_twd": "約 NT$580-800",
    "save_stars": 5,
    "reason": "韓國限定城市杯，收藏控必收，台灣買不到",
    "where": ["星巴克"],
    "maps_query": "스타벅스",
    "region_note": "韓國星巴克限定，台灣無販售",
    "editor_rank": 40
  },
  {
    "id": "kr2-21",
    "country": "kr",
    "name_zh": "真露 Chamisul 燒酒",
    "name_local": "진로 참이슬",
    "category": "souvenir",
    "emoji": "🥂",
    "price_local": "₩1,500-2,500",
    "price_twd": "約 NT$35-60",
    "save_stars": 5,
    "reason": "國民燒酒，便利商店銅板價，帶回台灣超划算",
    "where": ["便利商店", "樂天超市"],
    "maps_query": "편의점",
    "region_note": "酒類，未成年勿飲；出境限量申報",
    "editor_rank": 41
  },
  {
    "id": "kr2-22",
    "country": "kr",
    "name_zh": "傳統蜜糖藥果",
    "name_local": "약과",
    "category": "souvenir",
    "emoji": "🍯",
    "price_local": "₩5,000-12,000",
    "price_twd": "約 NT$115-280",
    "save_stars": 3,
    "reason": "GD同款傳統蜜糖果子，酥脆香甜爆紅伴手禮",
    "where": ["Olive Young", "樂天超市", "便利商店"],
    "maps_query": "올리브영",
    "region_note": null,
    "editor_rank": 42
  },
  {
    "id": "kr2-23",
    "country": "kr",
    "name_zh": "Artbox 文創文具小物",
    "name_local": "아트박스 문구",
    "category": "souvenir",
    "emoji": "✏️",
    "price_local": "₩3,000-15,000",
    "price_twd": "約 NT$70-350",
    "save_stars": 3,
    "reason": "設計文具小物，年輕有趣，挑禮物好逛",
    "where": ["Artbox"],
    "maps_query": "아트박스",
    "region_note": null,
    "editor_rank": 43
  },
  {
    "id": "kr2-24",
    "country": "kr",
    "name_zh": "三養 火辣雞肉炒麵",
    "name_local": "삼양 불닭볶음면",
    "category": "snacks",
    "emoji": "🌶️",
    "price_local": "₩4,000-6,000",
    "price_twd": "約 NT$90-140",
    "save_stars": 4,
    "reason": "地表最辣炒麵，辣控挑戰必買，口味超多",
    "where": ["樂天超市", "便利商店"],
    "maps_query": "롯데마트",
    "region_note": null,
    "editor_rank": 44
  },
  {
    "id": "kr2-25",
    "country": "kr",
    "name_zh": "海太 蜂蜜奶油洋芋片",
    "name_local": "해태 허니버터칩",
    "category": "snacks",
    "emoji": "🥔",
    "price_local": "₩1,500-3,000",
    "price_twd": "約 NT$35-70",
    "save_stars": 4,
    "reason": "鹹甜奶油香爆棚，一開就停不下來",
    "where": ["樂天超市", "便利商店"],
    "maps_query": "롯데마트",
    "region_note": null,
    "editor_rank": 45
  },
  {
    "id": "kr2-26",
    "country": "kr",
    "name_zh": "農心 蝦味先",
    "name_local": "농심 새우깡",
    "category": "snacks",
    "emoji": "🍤",
    "price_local": "₩1,500-2,500",
    "price_twd": "約 NT$35-60",
    "save_stars": 3,
    "reason": "韓版蝦味先，酥脆涮嘴，配啤酒一流",
    "where": ["樂天超市", "便利商店"],
    "maps_query": "롯데마트",
    "region_note": null,
    "editor_rank": 46
  },
  {
    "id": "kr2-27",
    "country": "kr",
    "name_zh": "樂天 Pepero 餅乾棒",
    "name_local": "롯데 빼빼로",
    "category": "snacks",
    "emoji": "🥨",
    "price_local": "₩1,500-2,500",
    "price_twd": "約 NT$35-60",
    "save_stars": 3,
    "reason": "國民餅乾棒，口味多又好分享，伴手禮首選",
    "where": ["樂天超市", "便利商店"],
    "maps_query": "롯데마트",
    "region_note": null,
    "editor_rank": 47
  },
  {
    "id": "kr2-28",
    "country": "kr",
    "name_zh": "DELIGHT PROJECT 貝果餅乾",
    "name_local": "딜라이트 프로젝트 베이글칩",
    "category": "snacks",
    "emoji": "🥯",
    "price_local": "₩3,000-5,000",
    "price_twd": "約 NT$70-115",
    "save_stars": 4,
    "reason": "Olive Young零食銷售冠軍，酥脆貝果香一包接一包",
    "where": ["Olive Young"],
    "maps_query": "올리브영",
    "region_note": "Olive Young 熱銷第一，僅該通路有售",
    "editor_rank": 48
  },
  {
    "id": "kr2-29",
    "country": "kr",
    "name_zh": "樂天 Binch 巧克力餅乾",
    "name_local": "롯데 빈츠",
    "category": "snacks",
    "emoji": "🍫",
    "price_local": "₩3,000-5,000",
    "price_twd": "約 NT$70-115",
    "save_stars": 3,
    "reason": "濃郁巧克力餅乾，入口即化，長輩小孩都愛",
    "where": ["樂天超市", "便利商店"],
    "maps_query": "롯데마트",
    "region_note": null,
    "editor_rank": 49
  },
  {
    "id": "kr2-30",
    "country": "kr",
    "name_zh": "Maxim KANU 即溶美式咖啡",
    "name_local": "맥심 카누",
    "category": "snacks",
    "emoji": "☕",
    "price_local": "₩8,000-15,000",
    "price_twd": "約 NT$180-350",
    "save_stars": 4,
    "reason": "孔劉代言即溶美式，隨手一包香醇不苦",
    "where": ["樂天超市", "便利商店"],
    "maps_query": "롯데마트",
    "region_note": null,
    "editor_rank": 50
  }
]
